gwerks/__init__.py
gwerks/aws.py
gwerks/builds.py
gwerks/cli.py
gwerks/decorators.py
gwerks/docker.py
gwerks/messaging.py
gwerks-2025.2.1738909155.dist-info/entry_points.txt
gwerks-2025.2.1738909155.dist-info/WHEEL
gwerks-2025.2.1738909155.dist-info/METADATA
gwerks-2025.2.1738909155.dist-info/RECORD
