Metadata-Version: 2.3
Name: gwerks
Version: 2025.2.1738909155
Summary: 'Lightweight python modules useful in most projects'
Author-email: Ron Glasmann <ron@glasmann.net>
Requires-Dist: boto3
Requires-Dist: tenacity
